rgb_mqtt/__init__.py
rgb_mqtt/args/__init__.py
rgb_mqtt/device_config.yaml
rgb_mqtt/leds/__init__.py
rgb_mqtt/logger/__init__.py
rgb_mqtt/mqtt/__init__.py
rgb_mqtt/utils/__init__.py
rgb_mqtt-1.0.0rc4.dist-info/METADATA
rgb_mqtt-1.0.0rc4.dist-info/WHEEL
rgb_mqtt-1.0.0rc4.dist-info/entry_points.txt
rgb_mqtt-1.0.0rc4.dist-info/RECORD
