Metadata-Version: 2.3
Name: rgb_mqtt
Version: 1.0.0rc4
Summary: This package makes it possible to control various types of LED strips with a homeassistant mqtt instance
License: Apache-2.0
Author: Guillaume Richard
Author-email: lord0gnome@gmail.com
Requires-Python: >=3.10,<4.0
Classifier: License :: OSI Approved :: Apache Software License
Classifier: Programming Language :: Python :: 3
Classifier: Programming Language :: Python :: 3.10
Classifier: Programming Language :: Python :: 3.11
Classifier: Programming Language :: Python :: 3.12
Classifier: Programming Language :: Python :: 3.13
Requires-Dist: RPi.GPIO (>=0.7.1,<0.8.0)
Requires-Dist: paho-mqtt (>=2.1.0,<3.0.0)
Requires-Dist: python-dotenv (>=1.0.1,<2.0.0)
Requires-Dist: pyyaml (>=6.0.2,<7.0.0)
